mseep_firstcycling-0.1.2.dist-info/licenses/LICENSE
tests/__init__.py
tests/test_rider_search.py
tests/debug/__init__.py
tests/debug/debug_monuments.py
mseep_firstcycling-0.1.2.dist-info/METADATA
mseep_firstcycling-0.1.2.dist-info/WHEEL
mseep_firstcycling-0.1.2.dist-info/top_level.txt
mseep_firstcycling-0.1.2.dist-info/RECORD
